_pyjxc.cp310-win_amd64.pyd
_pyjxc/__init__.pyi
_pyjxc/py.typed
jxc/__init__.py
jxc/decode.py
jxc/encode.py
jxc/py.typed
jxc/util.py
jxc-0.9.1.dist-info/LICENSE.MIT
jxc-0.9.1.dist-info/METADATA
jxc-0.9.1.dist-info/WHEEL
jxc-0.9.1.dist-info/top_level.txt
jxc-0.9.1.dist-info/RECORD
