Metadata-Version: 2.1
Name: jxc
Version: 0.9.1
Summary: JXC is a structured data language similar to JSON, but with a focus on being expressive, extensible, and human-friendly.
Author-email: Judd Cohen <jcohen@juddnet.com>
Project-URL: Homepage, https://jxc.juddnet.com
Project-URL: Documentation, https://jxc.juddnet.com/jxc_python_library.html
Project-URL: Bug Tracker, https://github.com/juddc/jxc/issues
Classifier: Programming Language :: Python :: 3
Classifier: License :: OSI Approved :: MIT License
Classifier: Operating System :: OS Independent
Classifier: Development Status :: 4 - Beta
Requires-Python: >=3.7
License-File: LICENSE.MIT
